easework/__init__.py
easework-0.6.1.dist-info/LICENSE.txt
easework-0.6.1.dist-info/METADATA
easework-0.6.1.dist-info/WHEEL
easework-0.6.1.dist-info/top_level.txt
easework-0.6.1.dist-info/RECORD
