Metadata-Version: 2.1
Name: easework
Version: 0.6.1
Summary: Python package that makes your work easy
Home-page: https://github.com/Dimi-nutive/easework
Author: Akul
Author-email: easework25@gmail.com
License: UNKNOWN
Platform: UNKNOWN
Requires-Dist: pillow
Requires-Dist: opencv-python
